matching/__init__.py
matching/__main__.py
matching/export.py
matching/factory.py
matching/match.py
matching/mentee.py
matching/mentor.py
matching/person.py
matching/process.py
matching/rules/__init__.py
matching/rules/rule.py
mentor_match-7.0.1.dist-info/METADATA
mentor_match-7.0.1.dist-info/WHEEL
mentor_match-7.0.1.dist-info/top_level.txt
mentor_match-7.0.1.dist-info/RECORD
