Metadata-Version: 2.1
Name: mentor-match
Version: 7.0.1
Summary: A series of classes to match mentors and mentees
Author: Jonathan Kerr
Author-email: jonathan.drew.kerr@gmail.com
License: MIT
Classifier: License :: OSI Approved :: MIT License
Classifier: Programming Language :: Python :: 3
Classifier: Programming Language :: Python :: 3.7
Requires-Dist: munkres
